[
    {
        "name": "Skittish Opilion",
        "code": "ravine-1",
        "frontImage": "https://ik.imagekit.io/cardtable/tr:w-400/earthborne_rangers/path/ravine/ravine_1.png",
        "backImage": "https://ik.imagekit.io/cardtable/tr:w-400/earthborne_rangers/misc/earthborne_rangers_path_card_back.png",
        "setType": "Path Sets",
        "set": "ravine"
    },
    {
        "name": "Skittish Opilion",
        "code": "ravine-2",
        "frontImage": "https://ik.imagekit.io/cardtable/tr:w-400/earthborne_rangers/path/ravine/ravine_2.png",
        "backImage": "https://ik.imagekit.io/cardtable/tr:w-400/earthborne_rangers/misc/earthborne_rangers_path_card_back.png",
        "setType": "Path Sets",
        "set": "ravine"
    },
    {
        "name": "Nycta Bats",
        "code": "ravine-3",
        "frontImage": "https://ik.imagekit.io/cardtable/tr:w-400/earthborne_rangers/path/ravine/ravine_3.png",
        "backImage": "https://ik.imagekit.io/cardtable/tr:w-400/earthborne_rangers/misc/earthborne_rangers_path_card_back.png",
        "setType": "Path Sets",
        "set": "ravine"
    },
    {
        "name": "Nycta Bats",
        "code": "ravine-4",
        "frontImage": "https://ik.imagekit.io/cardtable/tr:w-400/earthborne_rangers/path/ravine/ravine_4.png",
        "backImage": "https://ik.imagekit.io/cardtable/tr:w-400/earthborne_rangers/misc/earthborne_rangers_path_card_back.png",
        "setType": "Path Sets",
        "set": "ravine"
    },
    {
        "name": "Tryptafolium",
        "code": "ravine-5",
        "frontImage": "https://ik.imagekit.io/cardtable/tr:w-400/earthborne_rangers/path/ravine/ravine_5.png",
        "backImage": "https://ik.imagekit.io/cardtable/tr:w-400/earthborne_rangers/misc/earthborne_rangers_path_card_back.png",
        "setType": "Path Sets",
        "set": "ravine"
    },
    {
        "name": "Tryptafolium",
        "code": "ravine-6",
        "frontImage": "https://ik.imagekit.io/cardtable/tr:w-400/earthborne_rangers/path/ravine/ravine_6.png",
        "backImage": "https://ik.imagekit.io/cardtable/tr:w-400/earthborne_rangers/misc/earthborne_rangers_path_card_back.png",
        "setType": "Path Sets",
        "set": "ravine"
    },
    {
        "name": "Loose Boulders",
        "code": "ravine-7",
        "frontImage": "https://ik.imagekit.io/cardtable/tr:w-400/earthborne_rangers/path/ravine/ravine_7.png",
        "backImage": "https://ik.imagekit.io/cardtable/tr:w-400/earthborne_rangers/misc/earthborne_rangers_path_card_back.png",
        "setType": "Path Sets",
        "set": "ravine"
    },
    {
        "name": "Loose Boulders",
        "code": "ravine-8",
        "frontImage": "https://ik.imagekit.io/cardtable/tr:w-400/earthborne_rangers/path/ravine/ravine_8.png",
        "backImage": "https://ik.imagekit.io/cardtable/tr:w-400/earthborne_rangers/misc/earthborne_rangers_path_card_back.png",
        "setType": "Path Sets",
        "set": "ravine"
    },
    {
        "name": "Web Wall",
        "code": "ravine-9",
        "frontImage": "https://ik.imagekit.io/cardtable/tr:w-400/earthborne_rangers/path/ravine/ravine_9.png",
        "backImage": "https://ik.imagekit.io/cardtable/tr:w-400/earthborne_rangers/misc/earthborne_rangers_path_card_back.png",
        "setType": "Path Sets",
        "set": "ravine"
    },
    {
        "name": "Web Wall",
        "code": "ravine-10",
        "frontImage": "https://ik.imagekit.io/cardtable/tr:w-400/earthborne_rangers/path/ravine/ravine_10.png",
        "backImage": "https://ik.imagekit.io/cardtable/tr:w-400/earthborne_rangers/misc/earthborne_rangers_path_card_back.png",
        "setType": "Path Sets",
        "set": "ravine"
    },
    {
        "name": "Fraying Rope Bridge",
        "code": "ravine-11",
        "frontImage": "https://ik.imagekit.io/cardtable/tr:w-400/earthborne_rangers/path/ravine/ravine_11.png",
        "backImage": "https://ik.imagekit.io/cardtable/tr:w-400/earthborne_rangers/misc/earthborne_rangers_path_card_back.png",
        "setType": "Path Sets",
        "set": "ravine"
    },
    {
        "name": "Talus Cave",
        "code": "ravine-12",
        "frontImage": "https://ik.imagekit.io/cardtable/tr:w-400/earthborne_rangers/path/ravine/ravine_12.png",
        "backImage": "https://ik.imagekit.io/cardtable/tr:w-400/earthborne_rangers/misc/earthborne_rangers_path_card_back.png",
        "setType": "Path Sets",
        "set": "ravine"
    }
]